BatchImageResize-0.3.7.dist-info/DESCRIPTION.rst
BatchImageResize-0.3.7.dist-info/METADATA
BatchImageResize-0.3.7.dist-info/RECORD
BatchImageResize-0.3.7.dist-info/WHEEL
BatchImageResize-0.3.7.dist-info/entry_points.txt
BatchImageResize-0.3.7.dist-info/metadata.json
BatchImageResize-0.3.7.dist-info/top_level.txt
batch_image_resize/__init__.py
batch_image_resize/core.py
batch_image_resize/resize_console.py
batch_image_resize/resize_qt5.py
batch_image_resize/utils.py
batch_image_resize/ui/MainWindow.py
batch_image_resize/ui/__init__.py
