Metadata-Version: 2.0
Name: BatchImageResize
Version: 0.3.7
Summary: Batch resize and compress images with Qt5 GUI.
Home-page: https://github.com/thunderamur/batch-image-resize
Author: Ramil Minnigaliev
Author-email: minnigaliev-r@yandex.ru
License: MIT
Keywords: batch image resize,resize image
Platform: UNKNOWN
Requires-Python: >=3.5
Requires-Dist: pillow (>=5.0)
Requires-Dist: PyQt5 (>=5.9)
